{
  "$schema": "https://schema.management.azure.com/schemas/2019-04-01/deploymentParameters.json#",
  "contentVersion": "1.0.0.0",
  "parameters": {
    "location": { "value": "northeurope" },
    "rgName": { "value": "rg-platform-prod" },
    "vnetName": { "value": "vnet-platform-prod" },
    "vnetAddressPrefix": { "value": "10.20.0.0/16" },
    "subnetName": { "value": "default" },
    "subnetPrefix": { "value": "10.20.1.0/24" },
    "vmRgName": { "value": "rg-compute-prod" },
    "vmName": { "value": "vm-prod-01" },
    "nicName": { "value": "nic-prod-01" },
    "vmSize": { "value": "Standard_B2s" },
    "adminPassword": { "value": "ReplaceWithAStrongPassword123!" }
  }
}
